data_analyzer_mcp_server/__init__.py
data_analyzer_mcp_server/__main__.py
data_analyzer_mcp_server/cli.py
data_analyzer_mcp_server/core.py
data_analyzer_mcp_server-0.1.0.dist-info/METADATA
data_analyzer_mcp_server-0.1.0.dist-info/WHEEL
data_analyzer_mcp_server-0.1.0.dist-info/entry_points.txt
data_analyzer_mcp_server-0.1.0.dist-info/top_level.txt
data_analyzer_mcp_server-0.1.0.dist-info/RECORD
