Metadata-Version: 2.4
Name: data-analyzer-mcp-server
Version: 0.1.0
Summary: data-analyzer-mcp-server
Requires-Python: >=3.11
Requires-Dist: matplotlib>=3.10.6
Requires-Dist: mcp[cli]>=1.14.0
Requires-Dist: pandas>=2.3.2
Requires-Dist: seaborn>=0.13.2
Requires-Dist: twine>=6.1.0
Requires-Dist: openpyxl>=3.1.5
